autoxgb/__init__.py
autoxgb/api.py
autoxgb/autoxgb.py
autoxgb/enums.py
autoxgb/logger.py
autoxgb/metrics.py
autoxgb/params.py
autoxgb/predict.py
autoxgb/schemas.py
autoxgb/utils.py
autoxgb/cli/__init__.py
autoxgb/cli/autoxgb.py
autoxgb/cli/predict.py
autoxgb/cli/serve.py
autoxgb/cli/train.py
autoxgb-0.2.2.dist-info/LICENSE
autoxgb-0.2.2.dist-info/METADATA
autoxgb-0.2.2.dist-info/WHEEL
autoxgb-0.2.2.dist-info/entry_points.txt
autoxgb-0.2.2.dist-info/top_level.txt
autoxgb-0.2.2.dist-info/RECORD
