Metadata-Version: 2.1
Name: autoxgb
Version: 0.2.2
Summary: autoxgb: tuning xgboost with optuna
Home-page: https://github.com/abhishekkrthakur/autoxgb
Author: Abhishek Thakur
Author-email: abhishek4@gmail.com
License: Apache 2.0
Platform: linux
Platform: unix
Requires-Python: >=3.6
License-File: LICENSE
Requires-Dist: fastapi (==0.70.0)
Requires-Dist: loguru (==0.5.3)
Requires-Dist: numpy (==1.21.3)
Requires-Dist: optuna (==2.10.0)
Requires-Dist: pyarrow (==6.0.0)
Requires-Dist: pydantic (==1.8.2)
Requires-Dist: joblib (==1.1.0)
Requires-Dist: pandas (==1.3.4)
Requires-Dist: scikit-learn (==1.0.1)
Requires-Dist: uvicorn (==0.15.0)
Requires-Dist: xgboost (==1.5.0)
